jsharpe/__init__.py
jsharpe/sharpe.py
jsharpe-0.4.0.dist-info/METADATA
jsharpe-0.4.0.dist-info/WHEEL
jsharpe-0.4.0.dist-info/licenses/LICENSE
jsharpe-0.4.0.dist-info/RECORD
