Metadata-Version: 2.4
Name: jsharpe
Version: 0.4.0
Summary: Probabilistic Sharpe ratio and related statistics.
Project-URL: repository, https://github.com/tschm/jsharpe
Project-URL: homepage, https://github.com/tschm/jsharpe
Project-URL: issues, https://github.com/tschm/jsharpe/issues
Author-email: Thomas Schmelzer <thomas@jqr.ae>
License: MIT License
License-File: LICENSE
Keywords: Sharpe ratio,quant,risk,statistics
Classifier: License :: OSI Approved :: MIT License
Classifier: Programming Language :: Python :: 3
Classifier: Programming Language :: Python :: 3.11
Classifier: Programming Language :: Python :: 3.12
Classifier: Programming Language :: Python :: 3.13
Classifier: Programming Language :: Python :: 3.14
Classifier: Topic :: Scientific/Engineering :: Mathematics
Requires-Python: >=3.11
Requires-Dist: numpy>=2.3.0
Requires-Dist: scipy>=1.16.3
